AliWenyuZaixianPiaowuJishuDaJiemi/README.md
AliWenyuZaixianPiaowuJishuDaJiemi/__init__.py
AliWenyuZaixianPiaowuJishuDaJiemi/__main__.py
AliWenyuZaixianPiaowuJishuDaJiemi/file.pdf
AliWenyuZaixianPiaowuJishuDaJiemi/index.html
ali_wenyu_zaixian_piaowu_jishu_da_jiemi-2024.3.5.0.dist-info/METADATA
ali_wenyu_zaixian_piaowu_jishu_da_jiemi-2024.3.5.0.dist-info/WHEEL
ali_wenyu_zaixian_piaowu_jishu_da_jiemi-2024.3.5.0.dist-info/entry_points.txt
ali_wenyu_zaixian_piaowu_jishu_da_jiemi-2024.3.5.0.dist-info/top_level.txt
ali_wenyu_zaixian_piaowu_jishu_da_jiemi-2024.3.5.0.dist-info/RECORD
